{
  "definitions": {
    "notes": {
      "n2": "Sonnet redo research (2026-04 v2) found no FWD 2.0 TFSI variant of Q5 8R in either the pre-facelift (auto-data gen 1121) or facelift (auto-data gen 4176) inventory. Only diesel 2.0 TDI is offered FWD. Marked no_confidence as a phantom EU configuration; row should be considered for removal.",
      "n4": "Verification backlog remains pending authoritative verification: official review did not yield a safe EU-only ratio update, so the existing entry is retained only as an unsupported reference."
    },
    "evidence_ref_sets": {
      "e1": [
        "legacy_research_sources:428937eb9fd6",
        "legacy_research_sources:4b4b833b364a",
        "legacy_research_sources:4b8ab423f879",
        "legacy_research_sources:5e252f7f436b",
        "legacy_research_sources:753cf52ddd21"
      ],
      "e2": [
        "secondary_technical_sources:q5-8r-pre-facelift-gen-autodata",
        "secondary_technical_sources:q5-8r-facelift-gen-autodata"
      ],
      "e3": [
        "legacy_research_sources:5c2e1a7d8f4b",
        "legacy_research_sources:6e9b3d4a1c2f",
        "legacy_research_sources:7d0c4e1b9a6f"
      ]
    }
  },
  "defaults": {
    "brand": "Audi",
    "type": "SUV",
    "market": "EU",
    "model_code": "8R",
    "body_code": "8R",
    "model_name": "Q5 (8R, 2011-2017)",
    "production_start_year": 2011,
    "production_end_year": 2017
  },
  "configurations": [
    {
      "id": "audi-8r-2-0-tfsi-eu-2011-dct7-fwd",
      "variant_name": "2.0 TFSI",
      "engine_code": "2.0L",
      "engine_name": "2.0L I4 TFSI Turbo",
      "fuel_type": "ICE",
      "drivetrain": {
        "confidence": "unverified",
        "notes_ref": "n2",
        "value": "FWD"
      },
      "transmission": {
        "confidence": "unverified",
        "notes_ref": "n2",
        "code": "DCT7",
        "name": "7-speed S tronic (DL501)"
      },
      "ratios": {
        "top_gear_ratio": {
          "confidence": "unverified",
          "notes_ref": "n2",
          "value": 0.68
        },
        "final_drive_front": {
          "confidence": "unverified",
          "notes_ref": "n2",
          "value": 3.444
        }
      },
      "tires": {
        "default": {
          "confidence": "unverified",
          "evidence_refs_ref": "e2",
          "notes_ref": "n2",
          "front": {
            "width_mm": 235.0,
            "aspect_pct": 55.0,
            "rim_in": 18.0
          },
          "default_axle_for_speed": "rear"
        },
        "options": [
          {
            "confidence": "unverified",
            "evidence_refs_ref": "e2",
            "notes_ref": "n2",
            "front": {
              "width_mm": 235.0,
              "aspect_pct": 55.0,
              "rim_in": 18.0
            },
            "default_axle_for_speed": "rear",
            "name": "Standard 18\""
          },
          {
            "confidence": "unverified",
            "evidence_refs_ref": "e2",
            "notes_ref": "n2",
            "front": {
              "width_mm": 245.0,
              "aspect_pct": 50.0,
              "rim_in": 19.0
            },
            "default_axle_for_speed": "rear",
            "name": "Sport 19\""
          },
          {
            "confidence": "unverified",
            "evidence_refs_ref": "e2",
            "notes_ref": "n2",
            "front": {
              "width_mm": 255.0,
              "aspect_pct": 45.0,
              "rim_in": 20.0
            },
            "default_axle_for_speed": "rear",
            "name": "S line 20\""
          }
        ]
      },
      "verification_notes": [
        {
          "note": "This research wave replaces the stale generic backlog note with row-specific contradiction evidence for the broad Q5 8R 2.0 TFSI front-wheel-drive S tronic placeholder. The recovered early Germany-market lineup article names only 2.0 TFSI quattro petrol states, and the stronger secondary facelift tables recovered in this packet also split 2.0 TFSI only into quattro exact slices. That means the broad 2011-2017 FWD DCT7 row is unsupported by the recovered packet and cannot inherit AWD petrol evidence, so production JSON remains unchanged.",
          "evidence_refs_ref": "e3"
        }
      ],
      "unresolved": [
        {
          "item": "Exact Audi Q5 8R 2.0 TFSI front-wheel-drive S tronic applicability across the represented EU 2011-2017 row span",
          "reason": "The recovered packet does not close any front-wheel-drive 2.0 TFSI Q5 state. The checked early official article names only quattro petrol states, and the stronger secondary facelift tables likewise recover only quattro exact slices.",
          "evidence_refs_ref": "e3"
        },
        {
          "item": "Represented-row front-wheel-drive DCT7 ratio, final-drive, and tire applicability",
          "reason": "Because no checked exact front-wheel-drive 2.0 TFSI Q5 state was recovered in this packet, the inherited DCT7 gearbox family, 0.680 top gear, 3.444 final drive, and 235/55 R18 tire mapping remain unsupported broad-row carryover values.",
          "evidence_refs_ref": "e3"
        }
      ],
      "configuration_confidence": "low_confidence",
      "order_analysis_policy": {
        "usable_for_engine_order": true,
        "usable_for_driveshaft_order": false,
        "usable_for_wheel_order": false,
        "requires_manual_confirmation": true
      }
    },
    {
      "id": "audi-8r-2-0-tfsi-eu-2011-zf8hp-fwd",
      "variant_name": "2.0 TFSI",
      "engine_code": "2.0L",
      "engine_name": "2.0L I4 TFSI Turbo",
      "fuel_type": "ICE",
      "drivetrain": {
        "confidence": "unverified",
        "notes_ref": "n2",
        "value": "FWD"
      },
      "transmission": {
        "confidence": "unverified",
        "notes_ref": "n2",
        "code": "ZF8HP",
        "name": "8-speed tiptronic (ZF 8HP)"
      },
      "ratios": {
        "top_gear_ratio": {
          "confidence": "unverified",
          "notes_ref": "n2",
          "value": 0.667
        },
        "final_drive_front": {
          "confidence": "unverified",
          "notes_ref": "n2",
          "value": 3.077
        }
      },
      "tires": {
        "default": {
          "confidence": "unverified",
          "evidence_refs_ref": "e2",
          "notes_ref": "n2",
          "front": {
            "width_mm": 235.0,
            "aspect_pct": 55.0,
            "rim_in": 18.0
          },
          "default_axle_for_speed": "rear"
        },
        "options": [
          {
            "confidence": "unverified",
            "evidence_refs_ref": "e2",
            "notes_ref": "n2",
            "front": {
              "width_mm": 235.0,
              "aspect_pct": 55.0,
              "rim_in": 18.0
            },
            "default_axle_for_speed": "rear",
            "name": "Standard 18\""
          },
          {
            "confidence": "unverified",
            "evidence_refs_ref": "e2",
            "notes_ref": "n2",
            "front": {
              "width_mm": 245.0,
              "aspect_pct": 50.0,
              "rim_in": 19.0
            },
            "default_axle_for_speed": "rear",
            "name": "Sport 19\""
          },
          {
            "confidence": "unverified",
            "evidence_refs_ref": "e2",
            "notes_ref": "n2",
            "front": {
              "width_mm": 255.0,
              "aspect_pct": 45.0,
              "rim_in": 20.0
            },
            "default_axle_for_speed": "rear",
            "name": "S line 20\""
          }
        ]
      },
      "verification_notes": [
        {
          "note": "This research wave replaces the stale generic backlog note with row-specific contradiction evidence for the broad Q5 8R 2.0 TFSI front-wheel-drive tiptronic placeholder. The recovered early Germany-market lineup article names only 2.0 TFSI quattro petrol states, and the stronger secondary facelift tables recovered in this packet also split 2.0 TFSI only into quattro exact slices. That means the broad 2011-2017 FWD ZF8HP row is unsupported by the recovered packet and cannot inherit AWD petrol evidence, so production JSON remains unchanged.",
          "evidence_refs_ref": "e3"
        }
      ],
      "unresolved": [
        {
          "item": "Exact Audi Q5 8R 2.0 TFSI front-wheel-drive tiptronic applicability across the represented EU 2011-2017 row span",
          "reason": "The recovered packet does not close any front-wheel-drive 2.0 TFSI Q5 state. The checked early official article names only quattro petrol states, and the stronger secondary facelift tables likewise recover only quattro exact slices.",
          "evidence_refs_ref": "e3"
        },
        {
          "item": "Represented-row front-wheel-drive ZF8HP ratio, final-drive, and tire applicability",
          "reason": "Because no checked exact front-wheel-drive 2.0 TFSI Q5 state was recovered in this packet, the inherited ZF8HP gearbox family, 0.667 top gear, 3.077 final drive, and 235/55 R18 tire mapping remain unsupported broad-row carryover values.",
          "evidence_refs_ref": "e3"
        }
      ],
      "configuration_confidence": "low_confidence",
      "order_analysis_policy": {
        "usable_for_engine_order": true,
        "usable_for_driveshaft_order": false,
        "usable_for_wheel_order": false,
        "requires_manual_confirmation": true
      }
    },
    {
      "id": "audi-8r-2-0-tfsi-quattro-eu-2011-dct7-awd",
      "variant_name": "2.0 TFSI quattro",
      "engine_code": "2.0L",
      "engine_name": "2.0L I4 TFSI Turbo",
      "fuel_type": "ICE",
      "drivetrain": {
        "confidence": "unverified",
        "value": "AWD"
      },
      "transmission": {
        "confidence": "family_default",
        "code": "DCT7",
        "name": "7-speed S tronic (DL501)"
      },
      "ratios": {
        "top_gear_ratio": {
          "confidence": "family_default",
          "value": 0.68
        },
        "final_drive_front": {
          "confidence": "family_default",
          "value": 3.444
        },
        "final_drive_rear": {
          "confidence": "family_default",
          "value": 3.444
        }
      },
      "tires": {
        "default": {
          "confidence": "family_default",
          "evidence_refs": [
            "legacy_research_sources:428937eb9fd6",
            "legacy_research_sources:4b4b833b364a",
            "legacy_research_sources:4b8ab423f879",
            "legacy_research_sources:5e252f7f436b",
            "legacy_research_sources:753cf52ddd21",
            "secondary_technical_sources:q5-8r-2-0-tfsi-211-dct7-autodata",
            "secondary_technical_sources:q5-8r-pre-facelift-gen-autodata"
          ],
          "front": {
            "width_mm": 235.0,
            "aspect_pct": 55.0,
            "rim_in": 18.0
          },
          "default_axle_for_speed": "rear"
        },
        "options": [
          {
            "confidence": "family_default",
            "evidence_refs_ref": "e1",
            "front": {
              "width_mm": 235.0,
              "aspect_pct": 55.0,
              "rim_in": 18.0
            },
            "default_axle_for_speed": "rear",
            "name": "Standard 18\""
          },
          {
            "confidence": "family_default",
            "evidence_refs_ref": "e1",
            "front": {
              "width_mm": 245.0,
              "aspect_pct": 50.0,
              "rim_in": 19.0
            },
            "default_axle_for_speed": "rear",
            "name": "Sport 19\""
          },
          {
            "confidence": "family_default",
            "evidence_refs_ref": "e1",
            "front": {
              "width_mm": 255.0,
              "aspect_pct": 45.0,
              "rim_in": 20.0
            },
            "default_axle_for_speed": "rear",
            "name": "S line 20\""
          }
        ]
      },
      "verification_notes": [
        {
          "note_ref": "n4",
          "evidence_refs_ref": "e1"
        }
      ],
      "unresolved": [
        {
          "item": "Audi Q5 (8R, 2011-2017) EU ratio-relevant variant mapping",
          "reason": "Authoritative per-model ratio extraction is still missing, so the no-guess policy keeps the existing values only as an unsupported reference.",
          "evidence_refs_ref": "e1"
        },
        {
          "item": "Audi Q5 (8R, 2011-2017) variant-level final_drive_ratio and top_gear_ratio confirmation",
          "reason": "Official source links logged, but values not programmatically verified in this pass.",
          "evidence_refs_ref": "e1"
        }
      ],
      "configuration_confidence": "low_confidence",
      "order_analysis_policy": {
        "usable_for_engine_order": true,
        "usable_for_driveshaft_order": false,
        "usable_for_wheel_order": false,
        "requires_manual_confirmation": true
      }
    },
    {
      "id": "audi-8r-2-0-tfsi-quattro-eu-2011-zf8hp-awd",
      "variant_name": "2.0 TFSI quattro",
      "engine_code": "2.0L",
      "engine_name": "2.0L I4 TFSI Turbo",
      "fuel_type": "ICE",
      "drivetrain": {
        "confidence": "unverified",
        "value": "AWD"
      },
      "transmission": {
        "confidence": "family_default",
        "code": "ZF8HP",
        "name": "8-speed tiptronic (ZF 8HP)"
      },
      "ratios": {
        "top_gear_ratio": {
          "confidence": "family_default",
          "value": 0.667
        },
        "final_drive_front": {
          "confidence": "family_default",
          "value": 3.077
        },
        "final_drive_rear": {
          "confidence": "family_default",
          "value": 3.077
        }
      },
      "tires": {
        "default": {
          "confidence": "family_default",
          "evidence_refs": [
            "legacy_research_sources:428937eb9fd6",
            "legacy_research_sources:4b4b833b364a",
            "legacy_research_sources:4b8ab423f879",
            "legacy_research_sources:5e252f7f436b",
            "legacy_research_sources:753cf52ddd21",
            "secondary_technical_sources:q5-8rf-2-0-tfsi-225-zf8hp-autodata",
            "secondary_technical_sources:q5-8r-facelift-gen-autodata"
          ],
          "front": {
            "width_mm": 235.0,
            "aspect_pct": 55.0,
            "rim_in": 18.0
          },
          "default_axle_for_speed": "rear"
        },
        "options": [
          {
            "confidence": "family_default",
            "evidence_refs_ref": "e1",
            "front": {
              "width_mm": 235.0,
              "aspect_pct": 55.0,
              "rim_in": 18.0
            },
            "default_axle_for_speed": "rear",
            "name": "Standard 18\""
          },
          {
            "confidence": "family_default",
            "evidence_refs_ref": "e1",
            "front": {
              "width_mm": 245.0,
              "aspect_pct": 50.0,
              "rim_in": 19.0
            },
            "default_axle_for_speed": "rear",
            "name": "Sport 19\""
          },
          {
            "confidence": "family_default",
            "evidence_refs_ref": "e1",
            "front": {
              "width_mm": 255.0,
              "aspect_pct": 45.0,
              "rim_in": 20.0
            },
            "default_axle_for_speed": "rear",
            "name": "S line 20\""
          }
        ]
      },
      "verification_notes": [
        {
          "note_ref": "n4",
          "evidence_refs_ref": "e1"
        }
      ],
      "unresolved": [
        {
          "item": "Audi Q5 (8R, 2011-2017) EU ratio-relevant variant mapping",
          "reason": "Authoritative per-model ratio extraction is still missing, so the no-guess policy keeps the existing values only as an unsupported reference.",
          "evidence_refs_ref": "e1"
        },
        {
          "item": "Audi Q5 (8R, 2011-2017) variant-level final_drive_ratio and top_gear_ratio confirmation",
          "reason": "Official source links logged, but values not programmatically verified in this pass.",
          "evidence_refs_ref": "e1"
        }
      ],
      "configuration_confidence": "low_confidence",
      "order_analysis_policy": {
        "usable_for_engine_order": true,
        "usable_for_driveshaft_order": false,
        "usable_for_wheel_order": false,
        "requires_manual_confirmation": true
      }
    },
    {
      "id": "audi-8r-3-0-tdi-quattro-eu-2011-dct7-awd",
      "variant_name": "3.0 TDI quattro",
      "engine_code": "3.0L",
      "engine_name": "3.0L V6 TDI Diesel",
      "fuel_type": "ICE",
      "drivetrain": {
        "confidence": "unverified",
        "value": "AWD"
      },
      "transmission": {
        "confidence": "family_default",
        "code": "DCT7",
        "name": "7-speed S tronic (DL501)"
      },
      "ratios": {
        "top_gear_ratio": {
          "confidence": "family_default",
          "value": 0.68
        },
        "final_drive_front": {
          "confidence": "family_default",
          "value": 3.444
        },
        "final_drive_rear": {
          "confidence": "family_default",
          "value": 3.444
        }
      },
      "tires": {
        "default": {
          "confidence": "family_default",
          "evidence_refs": [
            "legacy_research_sources:428937eb9fd6",
            "legacy_research_sources:4b4b833b364a",
            "legacy_research_sources:4b8ab423f879",
            "legacy_research_sources:5e252f7f436b",
            "legacy_research_sources:753cf52ddd21",
            "secondary_technical_sources:q5-8r-3-0-tdi-240-dct7-autodata",
            "secondary_technical_sources:q5-8rf-3-0-tdi-245-dct7-autodata"
          ],
          "front": {
            "width_mm": 235.0,
            "aspect_pct": 55.0,
            "rim_in": 18.0
          },
          "default_axle_for_speed": "rear"
        },
        "options": [
          {
            "confidence": "family_default",
            "evidence_refs_ref": "e1",
            "front": {
              "width_mm": 235.0,
              "aspect_pct": 55.0,
              "rim_in": 18.0
            },
            "default_axle_for_speed": "rear",
            "name": "Standard 18\""
          },
          {
            "confidence": "family_default",
            "evidence_refs_ref": "e1",
            "front": {
              "width_mm": 245.0,
              "aspect_pct": 50.0,
              "rim_in": 19.0
            },
            "default_axle_for_speed": "rear",
            "name": "Sport 19\""
          },
          {
            "confidence": "family_default",
            "evidence_refs_ref": "e1",
            "front": {
              "width_mm": 255.0,
              "aspect_pct": 45.0,
              "rim_in": 20.0
            },
            "default_axle_for_speed": "rear",
            "name": "S line 20\""
          }
        ]
      },
      "verification_notes": [
        {
          "note_ref": "n4",
          "evidence_refs_ref": "e1"
        }
      ],
      "unresolved": [
        {
          "item": "Audi Q5 (8R, 2011-2017) EU ratio-relevant variant mapping",
          "reason": "Authoritative per-model ratio extraction is still missing, so the no-guess policy keeps the existing values only as an unsupported reference.",
          "evidence_refs_ref": "e1"
        },
        {
          "item": "Audi Q5 (8R, 2011-2017) variant-level final_drive_ratio and top_gear_ratio confirmation",
          "reason": "Official source links logged, but values not programmatically verified in this pass.",
          "evidence_refs_ref": "e1"
        }
      ],
      "configuration_confidence": "low_confidence",
      "order_analysis_policy": {
        "usable_for_engine_order": true,
        "usable_for_driveshaft_order": false,
        "usable_for_wheel_order": false,
        "requires_manual_confirmation": true
      }
    },
    {
      "id": "audi-8r-3-0-tdi-quattro-eu-2011-zf8hp-awd",
      "variant_name": "3.0 TDI quattro",
      "engine_code": "3.0L",
      "engine_name": "3.0L V6 TDI Diesel",
      "fuel_type": "ICE",
      "drivetrain": {
        "confidence": "unverified",
        "value": "AWD"
      },
      "transmission": {
        "confidence": "family_default",
        "code": "ZF8HP",
        "name": "8-speed tiptronic (ZF 8HP)"
      },
      "ratios": {
        "top_gear_ratio": {
          "confidence": "family_default",
          "value": 0.667
        },
        "final_drive_front": {
          "confidence": "family_default",
          "value": 3.077
        },
        "final_drive_rear": {
          "confidence": "family_default",
          "value": 3.077
        }
      },
      "tires": {
        "default": {
          "confidence": "family_default",
          "evidence_refs": [
            "legacy_research_sources:428937eb9fd6",
            "legacy_research_sources:4b4b833b364a",
            "legacy_research_sources:4b8ab423f879",
            "legacy_research_sources:5e252f7f436b",
            "legacy_research_sources:753cf52ddd21",
            "secondary_technical_sources:q5-8rf-3-0-tdi-240-zf8hp-autodata",
            "secondary_technical_sources:q5-8r-facelift-gen-autodata"
          ],
          "front": {
            "width_mm": 235.0,
            "aspect_pct": 55.0,
            "rim_in": 18.0
          },
          "default_axle_for_speed": "rear"
        },
        "options": [
          {
            "confidence": "family_default",
            "evidence_refs_ref": "e1",
            "front": {
              "width_mm": 235.0,
              "aspect_pct": 55.0,
              "rim_in": 18.0
            },
            "default_axle_for_speed": "rear",
            "name": "Standard 18\""
          },
          {
            "confidence": "family_default",
            "evidence_refs_ref": "e1",
            "front": {
              "width_mm": 245.0,
              "aspect_pct": 50.0,
              "rim_in": 19.0
            },
            "default_axle_for_speed": "rear",
            "name": "Sport 19\""
          },
          {
            "confidence": "family_default",
            "evidence_refs_ref": "e1",
            "front": {
              "width_mm": 255.0,
              "aspect_pct": 45.0,
              "rim_in": 20.0
            },
            "default_axle_for_speed": "rear",
            "name": "S line 20\""
          }
        ]
      },
      "verification_notes": [
        {
          "note_ref": "n4",
          "evidence_refs_ref": "e1"
        }
      ],
      "unresolved": [
        {
          "item": "Audi Q5 (8R, 2011-2017) EU ratio-relevant variant mapping",
          "reason": "Authoritative per-model ratio extraction is still missing, so the no-guess policy keeps the existing values only as an unsupported reference.",
          "evidence_refs_ref": "e1"
        },
        {
          "item": "Audi Q5 (8R, 2011-2017) variant-level final_drive_ratio and top_gear_ratio confirmation",
          "reason": "Official source links logged, but values not programmatically verified in this pass.",
          "evidence_refs_ref": "e1"
        }
      ],
      "configuration_confidence": "low_confidence",
      "order_analysis_policy": {
        "usable_for_engine_order": true,
        "usable_for_driveshaft_order": false,
        "usable_for_wheel_order": false,
        "requires_manual_confirmation": true
      }
    }
  ]
}
